{
    "update_time": "23:01",
    "flights": [
        {
            "flight_number": "AC 7953",
            "origin_city": "Montréal YUL",
            "origin_time": "07:24",
            "destination_time": "08:41",
            "scheduled_time": "08:49",
            "status": "Arrived",
            "arrival_time_difference": "0:08"
        },
        {
            "flight_number": "AC 7955",
            "origin_city": "Montréal YUL",
            "origin_time": "08:23",
            "destination_time": "09:40",
            "scheduled_time": "09:49",
            "status": "Arrived",
            "arrival_time_difference": "0:09"
        },
        {
            "flight_number": "AC 7705",
            "origin_city": "Ottawa YOW",
            "origin_time": "09:35",
            "destination_time": "10:34",
            "scheduled_time": "10:44",
            "status": "Arrived",
            "arrival_time_difference": "0:10"
        },
        {
            "flight_number": "AC 7959",
            "origin_city": "Montréal YUL",
            "origin_time": "10:30",
            "destination_time": "11:44",
            "scheduled_time": "11:49",
            "status": "Arrived",
            "arrival_time_difference": "0:05"
        },
        {
            "flight_number": "AC 7965",
            "origin_city": "Montréal YUL",
            "origin_time": "13:27",
            "destination_time": "14:49",
            "scheduled_time": "14:49",
            "status": "Arrived",
            "arrival_time_difference": "0:00"
        },
        {
            "flight_number": "AC 7709",
            "origin_city": "Ottawa YOW",
            "origin_time": "14:27",
            "destination_time": "15:25",
            "scheduled_time": "15:44",
            "status": "Arrived",
            "arrival_time_difference": "0:19"
        },
        {
            "flight_number": "AC 7969",
            "origin_city": "Montréal YUL",
            "origin_time": "15:17",
            "destination_time": "16:29",
            "scheduled_time": "16:49",
            "status": "Arrived",
            "arrival_time_difference": "0:20"
        },
        {
            "flight_number": "AC 7711",
            "origin_city": "Ottawa YOW",
            "origin_time": "17:45",
            "destination_time": "18:41",
            "scheduled_time": "18:44",
            "status": "Arrived",
            "arrival_time_difference": "0:03"
        },
        {
            "flight_number": "AC 7975",
            "origin_city": "Montréal YUL",
            "origin_time": "18:22",
            "destination_time": "19:41",
            "scheduled_time": "19:49",
            "status": "Arrived",
            "arrival_time_difference": "0:08"
        },
        {
            "flight_number": "AC 7713",
            "origin_city": "Ottawa YOW",
            "origin_time": "19:35",
            "destination_time": "20:30",
            "scheduled_time": "20:44",
            "status": "Arrived",
            "arrival_time_difference": "0:14"
        },
        {
            "flight_number": "AC 7979",
            "origin_city": "Montréal YUL",
            "origin_time": "20:06",
            "destination_time": "21:25",
            "scheduled_time": "21:34",
            "status": "Arrived",
            "arrival_time_difference": "0:09"
        }
    ],
    "next_flight": null
}